{
	"color": 13393232,
	"title": "FRAPPE ORBITALE FUSANTE",
	"image":false,
	"thumbnail": "https://cdn.discordapp.com/attachments/1215438009479073812/1217557667971731558/HD2-OAS.png?ex=660475f1&is=65f200f1&hm=c13df625e1e4537903f802c13921ce8420b2c3211d402dc3d1fc8397b8dd6d71&",
	"field": [
		{
			"name": " ",
			"value": ":arrow_right: :arrow_right: :arrow_right:"
		},
		{
			"name": "Informations (après améliorations)",
			"value": "- Utilisation : Illimité\n- Temps de recharge : 2 minutes\n- Temps d'activation : 3 secondes\n- Niveau : 5\n- Prix : 4 000 R"
		},
		{
			"name": "Description",
			"value": "Un projectile qu explose dans les airs et provoque une pluie de shrapnels mortelle. Peui efficace contre les ennemis bénéficiant d'un louird blindage."
		},
		{
			"name": "Tag",
			"value": "- Explosif\n- Frappe Orbital\n- Perce blindage léger"
		}
	],
    "footerDate": "12/03/24",
    "footerUser":"Spatulox"
}
